README.md
setup.py
emailbob_twingate/__init__.py
emailbob_twingate/_inputs.py
emailbob_twingate/_utilities.py
emailbob_twingate/get_twingate_connector.py
emailbob_twingate/get_twingate_connectors.py
emailbob_twingate/get_twingate_group.py
emailbob_twingate/get_twingate_groups.py
emailbob_twingate/get_twingate_remote_network.py
emailbob_twingate/get_twingate_remote_networks.py
emailbob_twingate/get_twingate_resource.py
emailbob_twingate/get_twingate_resources.py
emailbob_twingate/get_twingate_security_policies.py
emailbob_twingate/get_twingate_security_policy.py
emailbob_twingate/get_twingate_service_accounts.py
emailbob_twingate/get_twingate_user.py
emailbob_twingate/get_twingate_users.py
emailbob_twingate/outputs.py
emailbob_twingate/provider.py
emailbob_twingate/pulumi-plugin.json
emailbob_twingate/py.typed
emailbob_twingate/resource.py
emailbob_twingate/twingate_connector.py
emailbob_twingate/twingate_connector_tokens.py
emailbob_twingate/twingate_group.py
emailbob_twingate/twingate_remote_network.py
emailbob_twingate/twingate_resource.py
emailbob_twingate/twingate_service_account.py
emailbob_twingate/twingate_service_account_key.py
emailbob_twingate/twingate_user.py
emailbob_twingate.egg-info/PKG-INFO
emailbob_twingate.egg-info/SOURCES.txt
emailbob_twingate.egg-info/dependency_links.txt
emailbob_twingate.egg-info/not-zip-safe
emailbob_twingate.egg-info/requires.txt
emailbob_twingate.egg-info/top_level.txt
emailbob_twingate/config/__init__.py
emailbob_twingate/config/vars.py