Metadata-Version: 2.1
Name: emailbob-twingate
Version: 0.0.3
Summary: A Pulumi package for creating and managing twingate cloud resources.
Home-page: https://www.twingate.com
License: Apache-2.0
Project-URL: Repository, https://github.com/emailbob/pulumi-twingate
Keywords: pulumi twingate category/infrastructure
Platform: UNKNOWN
Requires-Python: >=3.8
